sanic_healthcheck/__init__.py
sanic_healthcheck/checker.py
sanic_healthcheck/handlers.py
sanic_healthcheck/health.py
sanic_healthcheck/ready.py
sanic_healthcheck-0.1.1.dist-info/LICENSE
sanic_healthcheck-0.1.1.dist-info/METADATA
sanic_healthcheck-0.1.1.dist-info/WHEEL
sanic_healthcheck-0.1.1.dist-info/top_level.txt
sanic_healthcheck-0.1.1.dist-info/RECORD
