Metadata-Version: 2.1
Name: sanic-healthcheck
Version: 0.1.1
Summary: Health checks for your Sanic applications
Home-page: https://github.com/vapor-ware/sanic-healthcheck
Author: Erick Daniszewski
Author-email: edaniszewski@gmail.com
License: MIT
Keywords: sanic health healthcheck liveness readiness
Platform: UNKNOWN
Classifier: Environment :: Web Environment
Classifier: Intended Audience :: Developers
Classifier: Natural Language :: English
Classifier: Programming Language :: Python
Classifier: Programming Language :: Python :: 3.6
Classifier: Programming Language :: Python :: 3.7
Requires-Python: >=3.6
Requires-Dist: sanic
